{"is_source_file": false, "format": "", "description": "", "external_files": [], "external_methods": [], "published": [], "classes": [], "methods": [], "calls": [], "search-terms": ["personal-notes-manager", "README.md", "documentation", "project description"], "state": 2, "file_id": 18, "knowledge_revision": 32, "git_revision": "7adbfbf79275dd2ed048c409bc8b76c895828f39", "hash": "1fcef6dae0c0c4c5099bffc3f0ff2c3f", "format-version": 4, "code-base-name": "notes_app_backend", "filename": "README.md", "revision_history": [{"32": "7adbfbf79275dd2ed048c409bc8b76c895828f39"}]}